oarepo_citations/__init__.py
oarepo_citations/i18n/__init__.py
oarepo_citations/i18n/webpack.py
oarepo_citations/i18n/semantic-ui/translations/oarepo_citations/i18next.js
oarepo_citations/i18n/semantic-ui/translations/oarepo_citations/messages/index.js
oarepo_citations/i18n/semantic-ui/translations/oarepo_citations/messages/cs/LC_MESSAGES/translations.json
oarepo_citations/i18n/semantic-ui/translations/oarepo_citations/messages/en/LC_MESSAGES/translations.json
oarepo_citations/i18n/translations/messages.mo
oarepo_citations/i18n/translations/messages.pot
oarepo_citations/i18n/translations/cs/LC_MESSAGES/messages.mo
oarepo_citations/i18n/translations/cs/LC_MESSAGES/messages.po
oarepo_citations/i18n/translations/en/LC_MESSAGES/messages.mo
oarepo_citations/i18n/translations/en/LC_MESSAGES/messages.po
oarepo_citations/resources/__init__.py
oarepo_citations/resources/csl/__init__.py
oarepo_citations/resources/csl/csl_to_bibtex.py
oarepo_citations/ui/__init__.py
oarepo_citations/ui/record_citations/__init__.py
oarepo_citations/ui/record_citations/webpack.py
oarepo_citations/ui/record_citations/semantic-ui/js/record_citations/components.jsx
oarepo_citations/ui/record_citations/semantic-ui/js/record_citations/custom-components.js
oarepo_citations/ui/record_citations/semantic-ui/js/record_citations/hooks.js
oarepo_citations/ui/record_citations/semantic-ui/js/record_citations/index.js
oarepo_citations/ui/record_citations/semantic-ui/js/record_citations/dropdown/index.js
oarepo_citations/ui/record_citations/semantic-ui/js/record_citations/dropdown/components/CitationField.jsx
oarepo_citations/ui/record_citations/semantic-ui/js/record_citations/dropdown/components/RecordCitations.jsx
oarepo_citations/ui/record_citations/semantic-ui/js/record_citations/dropdown/components/index.js
oarepo_citations/ui/record_citations/semantic-ui/js/record_citations/modal/index.js
oarepo_citations/ui/record_citations/semantic-ui/js/record_citations/modal/components/CitationList.jsx
oarepo_citations-1.0.2.dist-info/licenses/LICENSE
oarepo_citations-1.0.2.dist-info/METADATA
oarepo_citations-1.0.2.dist-info/WHEEL
oarepo_citations-1.0.2.dist-info/entry_points.txt
oarepo_citations-1.0.2.dist-info/top_level.txt
oarepo_citations-1.0.2.dist-info/RECORD
