Metadata-Version: 2.4
Name: oarepo-citations
Version: 1.0.2
Summary: Support for citations
License-File: LICENSE
Requires-Dist: oarepo-runtime
Requires-Dist: oarepo-ui
Provides-Extra: dev
Requires-Dist: oarepo-tools; extra == "dev"
Provides-Extra: tests
Requires-Dist: oarepo-ui; extra == "tests"
Dynamic: license-file
